libwaveform/__init__.py
libwaveform/__init__.pyi
libwaveform/amplitude_spectrum.tsv
libwaveform/flashcam.yaml
libwaveform/libwaveform.cpython-314t-x86_64-linux-gnu.so
libwaveform/multipmt.yaml
libwaveform/pulse_shape.tsv
libwaveform/time_spectrum.tsv
swgo_wave-0.2.4.dist-info/METADATA
swgo_wave-0.2.4.dist-info/WHEEL
swgo_wave-0.2.4.dist-info/RECORD
swgo_wave-0.2.4.dist-info/licenses/LICENSE
